ds_boost/__init__.py
ds_boost/ds_boost.py
ds_boost/logger.py
ds_boost-0.1.1.dist-info/LICENSE
ds_boost-0.1.1.dist-info/WHEEL
ds_boost-0.1.1.dist-info/METADATA
ds_boost-0.1.1.dist-info/RECORD
