Metadata-Version: 2.1
Name: ds-boost
Version: 0.1.1
Summary: Package for Practical & efficient Data Science in Python. Initially written for data-science-keras repo
License: MIT
Author: Angel Martinez-Tenor
Author-email: angelmtenor@gmail.com
Requires-Python: >=3.10,<4.0
Classifier: License :: OSI Approved :: MIT License
Classifier: Programming Language :: Python :: 3
Classifier: Programming Language :: Python :: 3.10
Classifier: Programming Language :: Python :: 3.11
Requires-Dist: jupyter (>=1.0.0,<2.0.0)
Requires-Dist: lightgbm (>=3.3.4)
Requires-Dist: matplotlib (>=3.6.3)
Requires-Dist: notebook (>=6.5.2)
Requires-Dist: pandas (>=1.5.0)
Requires-Dist: psutil (>=5.9.4)
Requires-Dist: py-cpuinfo (>=9.0.0)
Requires-Dist: pyarrow (>=9.0.0)
Requires-Dist: scikit-learn (>=1.2.0)
Requires-Dist: seaborn (>=0.12.2)
Requires-Dist: tensorflow (>=2.11.0); python_version >= "3.10" and python_version < "3.11"
